pyECSS/Component.py
pyECSS/ECSSManager.py
pyECSS/Entity.py
pyECSS/Event.py
pyECSS/System.py
pyECSS/__init__.py
pyECSS/_version.py
pyECSS/utilities.py
pyECSS/examples/__init__.py
pyECSS/tests/__init__.py
pyECSS/tests/test_ECSSManager.py
pyECSS/tests/test_EntityComponents.py
pyECSS/tests/test_System.py
pyECSS/tests/test_utilities.py
pyECSS-1.0.8.dist-info/LICENSE.txt
pyECSS-1.0.8.dist-info/METADATA
pyECSS-1.0.8.dist-info/WHEEL
pyECSS-1.0.8.dist-info/top_level.txt
pyECSS-1.0.8.dist-info/RECORD
