Metadata-Version: 2.1
Name: pyECSS
Version: 1.0.8
Summary: pyECSS (Entity Component Systems in a Scenegraph)
Home-page: https://github.com/papagiannakis/pyECSS
Author: George Papagiannakis
Author-email: papagian@csd.uoc.gr
Maintainer: Manos Kamarianakis
Maintainer-email: m.kamarianakis@gmail.com
License: Apache 2
Project-URL: Homepage, https://github.com/papagiannakis/pyECSS
Project-URL: Documentation, https://pyecss.readthedocs.io
Project-URL: Bug Tracker, https://github.com/papagiannakis/pyECSS
Project-URL: Source Code, https://github.com/papagiannakis/pyECSS
Keywords: ECS,Scenegraph,Python design patterns,Computer Graphics
Classifier: License :: OSI Approved :: Apache Software License
Classifier: Environment :: MacOS X
Classifier: Environment :: Win32 (MS Windows)
Classifier: Environment :: X11 Applications
Classifier: Operating System :: Microsoft :: Windows
Classifier: Operating System :: MacOS
Classifier: Operating System :: Unix
Classifier: Programming Language :: Python :: 3.9
Requires-Python: >=3.8,<3.10
License-File: LICENSE.txt
Requires-Dist: pip
Requires-Dist: setuptools (>=61)
Requires-Dist: wheel
Requires-Dist: numpy
Requires-Dist: scipy
